vizforge/__init__.py
vizforge/config.py
vizforge/version.py
vizforge/charts/__init__.py
vizforge/charts/area.py
vizforge/charts/bar.py
vizforge/charts/boxplot.py
vizforge/charts/bubble.py
vizforge/charts/funnel.py
vizforge/charts/heatmap.py
vizforge/charts/histogram.py
vizforge/charts/line.py
vizforge/charts/pie.py
vizforge/charts/radar.py
vizforge/charts/scatter.py
vizforge/charts/waterfall.py
vizforge/charts/2d/__init__.py
vizforge/charts/2d/area.py
vizforge/charts/2d/boxplot.py
vizforge/charts/2d/bubble.py
vizforge/charts/2d/funnel.py
vizforge/charts/2d/heatmap.py
vizforge/charts/2d/histogram.py
vizforge/charts/2d/radar.py
vizforge/charts/2d/waterfall.py
vizforge/charts/advanced/__init__.py
vizforge/charts/advanced/contour.py
vizforge/charts/advanced/parallel.py
vizforge/charts/advanced/sunburst.py
vizforge/charts/advanced/treemap.py
vizforge/charts/geo/__init__.py
vizforge/charts/geo/choropleth.py
vizforge/charts/geo/densitygeo.py
vizforge/charts/geo/flowmap.py
vizforge/charts/geo/linegeo.py
vizforge/charts/geo/scattergeo.py
vizforge/charts/network/__init__.py
vizforge/charts/network/dendrogram.py
vizforge/charts/network/graph.py
vizforge/charts/network/sankey.py
vizforge/charts/network/tree.py
vizforge/charts/realtime/__init__.py
vizforge/charts/realtime/animated.py
vizforge/charts/realtime/streaming.py
vizforge/charts/stats/__init__.py
vizforge/charts/stats/correlation.py
vizforge/charts/stats/feature_importance.py
vizforge/charts/stats/kde.py
vizforge/charts/stats/regression.py
vizforge/charts/stats/roc.py
vizforge/charts/stats/violin.py
vizforge/charts/threed/__init__.py
vizforge/charts/threed/cone.py
vizforge/charts/threed/isosurface.py
vizforge/charts/threed/mesh3d.py
vizforge/charts/threed/scatter3d.py
vizforge/charts/threed/surface.py
vizforge/charts/threed/volume.py
vizforge/core/__init__.py
vizforge/core/base.py
vizforge/core/export.py
vizforge/core/theme.py
vizforge/dashboard/__init__.py
vizforge/dashboard/components.py
vizforge-0.5.1.dist-info/licenses/LICENSE
vizforge-0.5.1.dist-info/METADATA
vizforge-0.5.1.dist-info/WHEEL
vizforge-0.5.1.dist-info/top_level.txt
vizforge-0.5.1.dist-info/RECORD
