Metadata-Version: 2.4
Name: vizforge
Version: 0.5.1
Summary: Production-grade data visualization library with zero AI dependencies
Author-email: Teyfik OZ <teyfikoz@example.com>
License: MIT
Project-URL: Homepage, https://github.com/teyfikoz/VizForge
Project-URL: Repository, https://github.com/teyfikoz/VizForge
Project-URL: Documentation, https://github.com/teyfikoz/VizForge/docs
Project-URL: Issues, https://github.com/teyfikoz/VizForge/issues
Keywords: visualization,plotting,charts,graphs,data-viz
Classifier: Development Status :: 4 - Beta
Classifier: Intended Audience :: Developers
Classifier: Intended Audience :: Science/Research
Classifier: Programming Language :: Python :: 3
Classifier: Programming Language :: Python :: 3.10
Classifier: Programming Language :: Python :: 3.11
Classifier: Programming Language :: Python :: 3.12
Classifier: Topic :: Scientific/Engineering :: Visualization
Classifier: Topic :: Software Development :: Libraries :: Python Modules
Requires-Python: >=3.10
License-File: LICENSE
Requires-Dist: plotly>=5.18.0
Requires-Dist: pandas>=2.0.0
Requires-Dist: numpy>=1.24.0
Requires-Dist: scipy>=1.10.0
Requires-Dist: scikit-learn>=1.3.0
Provides-Extra: dev
Requires-Dist: pytest>=7.0; extra == "dev"
Requires-Dist: pytest-cov>=4.0; extra == "dev"
Requires-Dist: black>=23.0; extra == "dev"
Requires-Dist: ruff>=0.1.0; extra == "dev"
Provides-Extra: geo
Requires-Dist: folium>=0.15.0; extra == "geo"
Requires-Dist: geopandas>=0.14.0; extra == "geo"
Provides-Extra: stats
Requires-Dist: scipy>=1.10.0; extra == "stats"
Requires-Dist: seaborn>=0.13.0; extra == "stats"
Provides-Extra: network
Requires-Dist: networkx>=3.0; extra == "network"
Requires-Dist: pyvis>=0.3.0; extra == "network"
Provides-Extra: export
Requires-Dist: kaleido>=0.2.1; extra == "export"
Requires-Dist: pillow>=10.0.0; extra == "export"
Provides-Extra: dashboard
Requires-Dist: plotly>=5.18.0; extra == "dashboard"
Provides-Extra: full
Requires-Dist: folium>=0.15.0; extra == "full"
Requires-Dist: geopandas>=0.14.0; extra == "full"
Requires-Dist: scipy>=1.10.0; extra == "full"
Requires-Dist: seaborn>=0.13.0; extra == "full"
Requires-Dist: networkx>=3.0; extra == "full"
Requires-Dist: pyvis>=0.3.0; extra == "full"
Requires-Dist: kaleido>=0.2.0; extra == "full"
Requires-Dist: pillow>=10.0.0; extra == "full"
Dynamic: license-file
